linnea/__init__.py
linnea/__main__.py
linnea/config.py
linnea/temporaries.py
linnea/utils.py
linnea/UnitTesting/__init__.py
linnea/UnitTesting/all_examples.py
linnea/algebra/InferenceOfProperties.py
linnea/algebra/__init__.py
linnea/algebra/consistency.py
linnea/algebra/equations.py
linnea/algebra/expression.py
linnea/algebra/properties.py
linnea/algebra/representations.py
linnea/algebra/transformations.py
linnea/algebra/utils.py
linnea/algebra/validity.py
linnea/code_generation/__init__.py
linnea/code_generation/utils.py
linnea/code_generation/memory/__init__.py
linnea/code_generation/memory/memory.py
linnea/code_generation/memory/storage_format.py
linnea/code_generation/memory/storage_format_conversions.py
linnea/derivation/CSEs.py
linnea/derivation/__init__.py
linnea/derivation/matrix_chain_solver.py
linnea/derivation/matrix_sum.py
linnea/derivation/partitioning.py
linnea/derivation/special_properties.py
linnea/derivation/tricks.py
linnea/derivation/utils.py
linnea/derivation/graph/__init__.py
linnea/derivation/graph/constructive.py
linnea/derivation/graph/exhaustive.py
linnea/derivation/graph/matrix_chain.py
linnea/derivation/graph/matrix_chain_derivation.py
linnea/derivation/graph/properties.py
linnea/derivation/graph/utils.py
linnea/derivation/graph/base/__init__.py
linnea/derivation/graph/base/base.py
linnea/derivation/graph/base/derivation.py
linnea/derivation/graph/base/expression.py
linnea/examples/PLDI.py
linnea/examples/__init__.py
linnea/examples/examples.py
linnea/frontend/AST_translation.py
linnea/frontend/__init__.py
linnea/frontend/export.py
linnea/frontend/parser.py
linnea/kernels/__init__.py
linnea/kernels/c/__init__.py
linnea/kernels/c/collections.py
linnea/kernels/c/factorizations.py
linnea/kernels/c/reductions.py
linnea/kernels/julia/__init__.py
linnea/kernels/julia/collections.py
linnea/kernels/julia/factorizations.py
linnea/kernels/julia/reductions.py
linnea/kernels/utils/__init__.py
linnea/kernels/utils/factorizations.py
linnea-0.1.dev1.dist-info/.DS_Store
linnea-0.1.dev1.dist-info/LICENSE
linnea-0.1.dev1.dist-info/METADATA
linnea-0.1.dev1.dist-info/WHEEL
linnea-0.1.dev1.dist-info/entry_points.txt
linnea-0.1.dev1.dist-info/top_level.txt
linnea-0.1.dev1.dist-info/zip-safe
linnea-0.1.dev1.dist-info/RECORD
