Metadata-Version: 2.1
Name: linnea
Version: 0.1.dev1
Summary: An experimental tool for the automatic generation of optimized code for linear algebra problems.
Home-page: https://github.com/HPAC/linnea
Author: Henrik Barthels
Author-email: barthels@aices.rwth-aachen.de
License: GPLv3
Platform: UNKNOWN
Classifier: Programming Language :: Python :: 3.6
Classifier: Programming Language :: Python :: 3.7
Classifier: License :: OSI Approved :: GNU Lesser General Public License v3 (LGPLv3)
Classifier: Operating System :: OS Independent
Requires-Python: >=3.6
Requires-Dist: matchpy (>=0.3)
Requires-Dist: tatsu (>=4.3)
